[
    {
        "dataApp1": {
            "oficinaSeleccionado": "2Barcelona",
            "tipoTramite": "Canjes de permiso de conduccion",
            "paisSeleccionado": "35",
            "nifnie": "Y3158587B",
            "nombre": "Samir",
            "primerApellido": "Akrim",
            "segundoApellido": "",
            "provinciaResidencia": "3Barcelona",
            "telefono": "",
            "fechaNacimiento": "26/07/1988",
            "fechaExpedicion": "27/01/2019",
            "lugarExpedicion": "TANGER",
            "numCartaIdentidad": "R9805672",
            "numPermisoMarroqui": "15/090901",
            "emailAviso": "overrimachi2001@gmail.com",
            "observaciones": ""
        },
        "dataApp2": {
            "oficinaSeleccionado": "2Barcelona",
            "tipoTramite": "Canjes de permiso de conduccion",
            "paisSeleccionado": "35",
            "nifnie": "Y8723070N",
            "nombre": "Farid",
            "primerApellido": "Alami",
            "segundoApellido": "",
            "provinciaResidencia": "3Barcelona",
            "telefono": "",
            "fechaNacimiento": "26/07/1988",
            "fechaExpedicion": "27/01/2019",
            "lugarExpedicion": "TANGER",
            "numCartaIdentidad": "K5438655",
            "numPermisoMarroqui": "15/655901",
            "emailAviso": "overrimachi2001@gmail.com",
            "observaciones": "Canie"
        }
    }
]